cherab-1.5.0-py3.7-nspkg.pth
cherab/core/VERSION
cherab/core/__init__.pxd
cherab/core/__init__.py
cherab/core/distribution.cpython-37m-x86_64-linux-gnu.so
cherab/core/distribution.pxd
cherab/core/distribution.pyx
cherab/core/species.cpython-37m-x86_64-linux-gnu.so
cherab/core/species.pxd
cherab/core/species.pyx
cherab/core/atomic/__init__.pxd
cherab/core/atomic/__init__.py
cherab/core/atomic/elements.cpython-37m-x86_64-linux-gnu.so
cherab/core/atomic/elements.pxd
cherab/core/atomic/elements.pyx
cherab/core/atomic/gaunt.cpython-37m-x86_64-linux-gnu.so
cherab/core/atomic/gaunt.pxd
cherab/core/atomic/gaunt.pyx
cherab/core/atomic/interface.cpython-37m-x86_64-linux-gnu.so
cherab/core/atomic/interface.pxd
cherab/core/atomic/interface.pyx
cherab/core/atomic/line.cpython-37m-x86_64-linux-gnu.so
cherab/core/atomic/line.pxd
cherab/core/atomic/line.pyx
cherab/core/atomic/rates.cpython-37m-x86_64-linux-gnu.so
cherab/core/atomic/rates.pxd
cherab/core/atomic/rates.pyx
cherab/core/atomic/zeeman.cpython-37m-x86_64-linux-gnu.so
cherab/core/atomic/zeeman.pxd
cherab/core/atomic/zeeman.pyx
cherab/core/atomic/data/maxwellian_free_free_gaunt_factor.json
cherab/core/atomic/data/lineshape/stark/d.json
cherab/core/atomic/data/lineshape/stark/h.json
cherab/core/atomic/data/lineshape/stark/t.json
cherab/core/atomic/data/lineshape/zeeman/parametrised/b.json
cherab/core/atomic/data/lineshape/zeeman/parametrised/be.json
cherab/core/atomic/data/lineshape/zeeman/parametrised/c.json
cherab/core/atomic/data/lineshape/zeeman/parametrised/d.json
cherab/core/atomic/data/lineshape/zeeman/parametrised/h.json
cherab/core/atomic/data/lineshape/zeeman/parametrised/he.json
cherab/core/atomic/data/lineshape/zeeman/parametrised/he3.json
cherab/core/atomic/data/lineshape/zeeman/parametrised/n.json
cherab/core/atomic/data/lineshape/zeeman/parametrised/ne.json
cherab/core/atomic/data/lineshape/zeeman/parametrised/o.json
cherab/core/beam/__init__.pxd
cherab-1.5.0.dist-info/AUTHORS.md
cherab-1.5.0.dist-info/LICENCE.txt
cherab-1.5.0.dist-info/METADATA
cherab-1.5.0.dist-info/WHEEL
cherab-1.5.0.dist-info/namespace_packages.txt
cherab-1.5.0.dist-info/top_level.txt
cherab-1.5.0.dist-info/RECORD
