Metadata-Version: 2.1
Name: cherab
Version: 1.5.0
Summary: Cherab spectroscopy framework
Home-page: https://github.com/cherab
License: EUPL 1.1
Project-URL: Tracker, https://github.com/cherab/core/issues
Project-URL: Documentation, https://cherab.github.io/documentation/
Classifier: Development Status :: 5 - Production/Stable
Classifier: Intended Audience :: Science/Research
Classifier: Intended Audience :: Education
Classifier: Intended Audience :: Developers
Classifier: Natural Language :: English
Classifier: Operating System :: POSIX :: Linux
Classifier: Programming Language :: Cython
Classifier: Programming Language :: Python :: 3
Classifier: Topic :: Scientific/Engineering :: Physics
License-File: LICENCE.txt
License-File: AUTHORS.md
Requires-Dist: numpy <2.0,>=1.14
Requires-Dist: scipy
Requires-Dist: matplotlib
Requires-Dist: raysect ==0.8.1.*
Provides-Extra: docs
Requires-Dist: cython ~=3.0 ; extra == 'docs'
Requires-Dist: sphinx ; extra == 'docs'
Requires-Dist: sphinx-rtd-theme ; extra == 'docs'
Requires-Dist: sphinx-tabs ; extra == 'docs'
